{
  "meta": {
    "generated_at": "2026-02-24T10:37:47.731131",
    "columns": [
      "scrip_code",
      "company_name",
      "price_announcement",
      "current_price",
      "current_mkt_cap_cr",
      "attachment_url"
    ],
    "failed_checks_count": 0,
    "lookback_years": 2
  },
  "data": {
    "Analyst Call Intimation": {
      "2026-02-20": [
        [
          "KWIL",
          "Kwality Wall's (India) Limited",
          27.73,
          26,
          6109,
          "https://nsearchives.nseindia.com/corporate/KWIL_20022026171556_SEIntimationOutcomeofBM_signed.pdf"
        ]
      ]
    },
    "Press Release": {
      "2026-02-20": [
        [
          "CEINSYS",
          "Ceinsys Tech Limited",
          1009.1,
          951.3,
          1697,
          "https://nsearchives.nseindia.com/corporate/CEINSYSTECH_20022026171054_Intimation_of_Press_Release_NSE_Listing_with_Bell_Ringing_Ceremony__.pdf"
        ]
      ]
    }
  }
}